typeevalpy_external_module/__init__.py
typeevalpy_external_module/ext.py
typeevalpy_external_module-1.0.0.dist-info/LICENSE
typeevalpy_external_module-1.0.0.dist-info/METADATA
typeevalpy_external_module-1.0.0.dist-info/WHEEL
typeevalpy_external_module-1.0.0.dist-info/top_level.txt
typeevalpy_external_module-1.0.0.dist-info/RECORD
