Metadata-Version: 2.1
Name: typeevalpy-external-module
Version: 1.0.0
Summary: External module for TypeEvalPy micro-benchmark for type inference
Author: 
Author-email: 
License: GPL-3.0
License-File: LICENSE
